daxpass/__init__.py
daxpass-2.1.dist-info/licenses/LICENSE
daxpass-2.1.dist-info/METADATA
daxpass-2.1.dist-info/WHEEL
daxpass-2.1.dist-info/top_level.txt
daxpass-2.1.dist-info/RECORD
