Metadata-Version: 2.4
Name: daxpass
Version: 2.1
Summary: A module used to create random passwords with customizable options and to encode/decode strings!
Author: Annie
License: MIT
Requires-Python: >=3.7
License-File: LICENSE
Dynamic: license-file
